pypagexml/__init__.py
pypagexml/core.py
pypagexml/ds/__init__.py
pypagexml/ds/gdscommon.py
pypagexml/ds/generated.py
pypagexml/ds/parse.py
pypagexml/ds/subclasses.py
pypagexml/ds/util.py
pypagexml-0.0.3.data/data/requirements.txt
pypagexml-0.0.3.dist-info/METADATA
pypagexml-0.0.3.dist-info/WHEEL
pypagexml-0.0.3.dist-info/top_level.txt
pypagexml-0.0.3.dist-info/RECORD
