Metadata-Version: 2.1
Name: pypagexml
Version: 0.0.3
Summary: UNKNOWN
Home-page: https://gitlab2.informatik.uni-wuerzburg.de/alg81dm/pypagexml.git
Author: Alexander Gehrke
Author-email: gehrke@informatik.uni-wuerzburg.de
License: UNKNOWN
Keywords: pagexml,page segmentation,layout
Platform: UNKNOWN
Classifier: Programming Language :: Python :: 3
Classifier: License :: OSI Approved :: GNU General Public License v3 or later (GPLv3+)
Classifier: License :: OSI Approved :: Apache Software License
Classifier: Intended Audience :: Science/Research
Requires-Dist: pillow
